pure_radix/__init__.py
pure_radix/py.typed
pure_radix-2.1.0.dist-info/METADATA
pure_radix-2.1.0.dist-info/WHEEL
pure_radix-2.1.0.dist-info/top_level.txt
pure_radix-2.1.0.dist-info/RECORD
