Metadata-Version: 2.1
Name: pure-radix
Version: 2.1.0
Summary: Generic radix tree implementation in pure Python
Author-email: Eduard Christian Dumitrescu <eduard.c.dumitrescu@gmail.com>
License: MIT License
Project-URL: Homepage, https://hydra.ecd.space/deaduard/pure_radix/
Project-URL: Changelog, https://hydra.ecd.space/deaduard/pure_radix/file?name=CHANGELOG.md&ci=trunk
Requires-Dist: attrs
